kitman/__init__.py
kitman/conf.py
kitman/exceptions.py
kitman/kitman.py
kitman/cli/__init__.py
kitman/core/__init__.py
kitman/core/commands.py
kitman/core/configs.py
kitman/core/converters.py
kitman/core/domain.py
kitman/core/dynamic.py
kitman/core/events.py
kitman/core/geo.py
kitman/core/handlers.py
kitman/core/queries.py
kitman/core/schemas.py
kitman/core/services.py
kitman/core/sdk/__init__.py
kitman/core/sdk/client.py
kitman/core/sdk/decorators.py
kitman/core/sdk/exceptions.py
kitman/core/sdk/request.py
kitman/core/sdk/response.py
kitman/kits/__init__.py
kitman/kits/iam/__init__.py
kitman/kits/iam/conf.py
kitman/kits/iam/deps.py
kitman/kits/iam/domain.py
kitman/kits/iam/exceptions.py
kitman/kits/iam/models.py
kitman/kits/iam/services.py
kitman/kits/iam/auth/__init__.py
kitman/kits/iam/auth/base.py
kitman/kits/iam/auth/proxy.py
kitman/kits/iam/auth/token.py
kitman/kits/templating/__init__.py
kitman/kits/templating/apps.py
kitman/kits/templating/dependency_resolvers.py
kitman/kits/templating/domain.py
kitman/kits/templating/exceptions.py
kitman/kits/templating/generics.py
kitman/kits/templating/models.py
kitman/kits/templating/services.py
kitman/kits/templating/templating.py
kitman/plugins/__init__.py
kitman/plugins/beanie/__init__.py
kitman/plugins/beanie/deps.py
kitman/plugins/beanie/domain.py
kitman/plugins/cors/__init__.py
kitman/plugins/cors/plugin.py
kitman/plugins/loguru/__init__.py
kitman/plugins/loguru/plugin.py
kitman/plugins/ormar/__init__.py
kitman/plugins/ormar/mixins.py
kitman/plugins/ormar/models.py
kitman/plugins/ormar/plugin.py
kitman/plugins/ory/__init__.py
kitman/plugins/ory/iam.py
kitman/plugins/ory/schemas.py
kitman/plugins/redis/__init__.py
kitman/plugins/redis/client.py
kitman/plugins/redis/plugin.py
kitman/plugins/stripe/__init__.py
kitman/plugins/stripe/domain.py
kitman/plugins/stripe/plugin.py
kitman/plugins/stripe/api/__init__.py
kitman/plugins/stripe/api/commands.py
kitman/plugins/stripe/api/queries.py
kitman-0.2.0.dist-info/LICENSE
kitman-0.2.0.dist-info/METADATA
kitman-0.2.0.dist-info/WHEEL
kitman-0.2.0.dist-info/top_level.txt
kitman-0.2.0.dist-info/RECORD
