Metadata-Version: 2.1
Name: kitman
Version: 0.2.0
Summary: A handy toolkit for building saas applications
Home-page: https://github.com/madskronborg/kitman
Author: Mads Kronborg
Author-email: me@madskronborg.dk
Project-URL: Bug Tracker, https://github.com/madskronborg/kitman/issues
Classifier: Programming Language :: Python :: 3
Classifier: License :: OSI Approved :: MIT License
Classifier: Operating System :: OS Independent
Requires-Python: >=3.10
License-File: LICENSE
Requires-Dist: pydantic[email,orjson]
Requires-Dist: pydantic-settings
Requires-Dist: pydantic-extra-types
Requires-Dist: ormar
Requires-Dist: fastapi
Requires-Dist: deepmerge
Requires-Dist: httpx[http2]
Requires-Dist: makefun
Requires-Dist: redis
Requires-Dist: hiredis
Requires-Dist: deepdiff
Requires-Dist: typer[all]
